orquestra/workflow_runtime/__init__.py
orquestra/workflow_runtime/py.typed
orquestra/workflow_runtime/_ray/__init__.py
orquestra/workflow_runtime/_ray/_build_workflow.py
orquestra/workflow_runtime/_ray/_client.py
orquestra/workflow_runtime/_ray/_dag.py
orquestra/workflow_runtime/_ray/_dirs.py
orquestra/workflow_runtime/_ray/_env.py
orquestra/workflow_runtime/_ray/_id_gen.py
orquestra/workflow_runtime/_ray/_ray_logs.py
orquestra/workflow_runtime/_ray/_ray_settings.py
orquestra/workflow_runtime/_ray/_wf_metadata.py
orquestra/workflow_runtime/_ray/_logs/__init__.py
orquestra/workflow_runtime/_ray/_logs/_markers.py
orquestra/workflow_runtime/_testing/_connections.py
orquestra_workflow_runtime-2.0.0.dist-info/METADATA
orquestra_workflow_runtime-2.0.0.dist-info/WHEEL
orquestra_workflow_runtime-2.0.0.dist-info/licenses/LICENSE
orquestra_workflow_runtime-2.0.0.dist-info/RECORD
