Metadata-Version: 2.3
Name: orquestra-workflow-runtime
Version: 2.0.0
Summary: Execute Orquestra workflows
Project-URL: Homepage, https://github.com/zapata-engineering/orquestra-sdk
Project-URL: Documentation, https://docs.orquestra.io
Project-URL: Repository, https://github.com/zapata-engineering/orquestra-sdk.git
Project-URL: Issues, https://github.com/zapata-engineering/orquestra-sdk/issues
Author-email: "Zapata Computing Inc." <info@zapata.ai>
License:                                  Apache License
License-File: LICENSE
Classifier: License :: OSI Approved :: Apache Software License
Classifier: Operating System :: OS Independent
Classifier: Programming Language :: Python :: 3
Classifier: Topic :: Scientific/Engineering
Requires-Python: >=3.8
Requires-Dist: importlib-metadata>=4.0
Requires-Dist: orquestra-workflow-shared~=2.0.0
Requires-Dist: pyarrow<16.0,>=10.0
Requires-Dist: pydantic>1.10.7
Requires-Dist: pyjwt>=2.6
Requires-Dist: requests>=2.28
Requires-Dist: typing-extensions>=4.1.0
Requires-Dist: wurlitzer>=3.0
Provides-Extra: all
Requires-Dist: async-timeout; extra == 'all'
Requires-Dist: ray[default]==2.30.0; extra == 'all'
Requires-Dist: virtualenv!=20.21.1,>=20.0.24; extra == 'all'
Provides-Extra: dashboard
Requires-Dist: async-timeout; extra == 'dashboard'
Requires-Dist: ray[default]==2.30.0; extra == 'dashboard'
Requires-Dist: virtualenv!=20.21.1,>=20.0.24; extra == 'dashboard'
Provides-Extra: dev
Requires-Dist: async-timeout; extra == 'dev'
Requires-Dist: black~=23.7; extra == 'dev'
Requires-Dist: diff-cover; extra == 'dev'
Requires-Dist: flake8-pyproject>=1.2.3; extra == 'dev'
Requires-Dist: flake8>=4.0.0; extra == 'dev'
Requires-Dist: freezegun; extra == 'dev'
Requires-Dist: isort~=5.9.0; extra == 'dev'
Requires-Dist: mypy~=0.910; extra == 'dev'
Requires-Dist: pydoclint; extra == 'dev'
Requires-Dist: pymarkdownlnt; extra == 'dev'
Requires-Dist: pyright; extra == 'dev'
Requires-Dist: pytest-cov>=2.12; extra == 'dev'
Requires-Dist: pytest-dependency; extra == 'dev'
Requires-Dist: pytest-httpserver; extra == 'dev'
Requires-Dist: pytest-timeout>=2.0.0; extra == 'dev'
Requires-Dist: pytest>=6.2; extra == 'dev'
Requires-Dist: ray[default]==2.30.0; extra == 'dev'
Requires-Dist: responses!=0.24,>=0.20; extra == 'dev'
Requires-Dist: ruff>=0.2.0; extra == 'dev'
Requires-Dist: types-requests; extra == 'dev'
Requires-Dist: types-setuptools; extra == 'dev'
Requires-Dist: virtualenv!=20.21.1,>=20.0.24; extra == 'dev'
Provides-Extra: ray
Requires-Dist: async-timeout; extra == 'ray'
Requires-Dist: ray[default]==2.30.0; extra == 'ray'
Requires-Dist: virtualenv!=20.21.1,>=20.0.24; extra == 'ray'
